<?xml version="1.0"?>
<Results version="1.0">
<ReportNode type="testrun">
<ReportNode type="Iteration">
<ReportNode type="Action">
<Data>
    <Name>Action1</Name>
    <Description />
    <StartTime>2022-07-05 16:10:58</StartTime>
    <Result>Done</Result>
    <InputParameters />
    <Extension>
      <IconKey>cb98da2a7d1545f89e27824c2d1bbcc8</IconKey>
      <IsPlainTextNodeName>True</IsPlainTextNodeName>
    </Extension>
  </Data>
</ReportNode>
<Data>
    <Name>Action0</Name>
    <Description />
    <StartTime>2022-07-05 16:10:53</StartTime>
    <Duration>5</Duration>
    <Result>Done</Result>
    <Extension>
      <IconKey>70c316bf62844f74b8462b689a09956a</IconKey>
      <IsPlainTextNodeName>True</IsPlainTextNodeName>
    </Extension>
    <Index>1</Index>
    <TestedApplications>
      <TestedApplication>
        <RuntimeEngineInfo />
        <Name>Google Chrome</Name>
        <Path>C:\Program Files\Google\Chrome\Application\chrome.exe</Path>
        <Version>103.0</Version>
        <Technology>web</Technology>
        <Reserved />
        <AdditionalInfos>
          <Info>http://3.65.165.176:8089/Xe/</Info>
        </AdditionalInfos>
      </TestedApplication>
    </TestedApplications>
  </Data>
</ReportNode>
<Data>
    <Name>DriverScriptDemo</Name>
    <ToolName>Micro Focus UFT One</ToolName>
    <ToolVersion>2021</ToolVersion>
    <ToolVersionStringLiteral>2021</ToolVersionStringLiteral>
    <Description />
    <StartTime>2022-07-05 16:10:31</StartTime>
    <Duration>27</Duration>
    <Result>Done</Result>
    <InputParameters />
    <Extension>
      <ParallelRunnerEnvInfo xmlns:xsi="http://www.w3.org/2001/XMLSchema-instance" xmlns:xsd="http://www.w3.org/2001/XMLSchema">
        <ID />
        <Manufacturer />
        <Model />
        <OsType />
        <OsVersion />
        <DesktopBrowser>Google Chrome</DesktopBrowser>
        <ErrorMessage />
      </ParallelRunnerEnvInfo>
      <IconKey>0188ce06fb1d4f1e8a5fc889bf27b77e</IconKey>
      <IsPlainTextNodeName>True</IsPlainTextNodeName>
    </Extension>
    <Environment>
      <Timezone>00:00:00</Timezone>
      <Locale>English (United States)</Locale>
      <User>Administrator</User>
      <CpuInfo>Intel(R) Xeon(R) Platinum 8175M CPU @ 2.50GHz</CpuInfo>
      <NumberOfCores>4</NumberOfCores>
      <TotalMemory>16196</TotalMemory>
      <HostName>EC2AMAZ-4I84599</HostName>
      <OSInfo>Windows Server 2019 (x64)</OSInfo>
    </Environment>
    <TestedApplications />
    <Links>
      <Link type="DataTable" reference="Default.xlsx" displayname="Default Data Table" />
    </Links>
  </Data>
</ReportNode>
<GeneralInfo>
    <ResultName>Res19</ResultName>
    <RunStartTime>2022-07-05 16:10:31</RunStartTime>
    <Timezone>00:00:00</Timezone>
    <OrchestrationToolName>Micro Focus UFT One</OrchestrationToolName>
    <OrchestrationToolVersion>2021</OrchestrationToolVersion>
    <OrchestrationToolVersionStringLiteral>2021</OrchestrationToolVersionStringLiteral>
  </GeneralInfo>
</Results>